{
  "TON": {
    "TON_Q1": {
      "QUESTION": ["원하는 톤 수를 알려주세요"],
      "QUEST": {
        "QUESTION_NUMBER": ["1", "2", "3", "4", "5", "6"],
        "QUESTION_VIEW": [
          "~1.2톤",
          "2.5톤 ~ 3.5톤",
          "4.5톤 ~ 7톤",
          "8톤 ~ 16톤",
          "19톤~",
          "트랙터"
        ]
      }
    }
  },
  "BRAND": {
    "BRAND_Q1": {
      "QUESTION": ["국산차와 외제차 중 구매하고 싶은 쪽을 알려주세요"],
      "QUEST": {
        "QUESTION_NUMBER": ["1", "2"],
        "QUESTION_VIEW": ["국산", "외제"]
      }
    }
  },
  "RELIABILITY": {
    "RELIABILITY_Q1": {
      "QUESTION": ["실매물 확인된 차량을 원하시나요?"],
      "QUEST": {
        "QUESTION_NUMBER": ["1", "2", "3", "4", "5"],
        "QUESTION_VIEW": [
          "아니요",
          "별로에요",
          "그냥 그래요",
          "괜찮은거 같아요",
          "좋아요"
        ]
      }
    },
    "RELIABILITY_Q2": {
      "QUESTION": ["종사원증 번호가 있는 딜러의 차량을 원하시나요?"],
      "QUEST": {
        "QUESTION_NUMBER": ["1", "2", "3", "4", "5"],
        "QUESTION_VIEW": [
          "아니요",
          "별로에요",
          "그냥 그래요",
          "괜찮은거 같아요",
          "좋아요"
        ]
      }
    },
    "RELIABILITY_Q3": {
      "QUESTION": ["일평균 등록 매물이 많은 딜러의 차량을 원하시나요?"],
      "QUEST": {
        "QUESTION_NUMBER": ["1", "2", "3", "4", "5"],
        "QUESTION_VIEW": [
          "아니요",
          "별로에요",
          "그냥 그래요",
          "괜찮은거 같아요",
          "좋아요"
        ]
      }
    },
    "RELIABILITY_Q4": {
      "QUESTION": ["헛걸음 보상 제공이 되는 딜러의 차량을 원하시나요?"],
      "QUEST": {
        "QUESTION_NUMBER": ["1", "2", "3", "4", "5"],
        "QUESTION_VIEW": [
          "아니요",
          "별로에요",
          "그냥 그래요",
          "괜찮은거 같아요",
          "좋아요"
        ]
      }
    },
    "RELIABILITY_Q5": {
      "QUESTION": ["아이트럭에서 정비 상태를 보장하는 인증 차량을 원하시나요?"],
      "QUEST": {
        "QUESTION_NUMBER": ["1", "2", "3", "4", "5"],
        "QUESTION_VIEW": [
          "아니요",
          "별로에요",
          "그냥 그래요",
          "괜찮은거 같아요",
          "좋아요"
        ]
      }
    }
  },
  "CONDITION": {
    "CONDITION_Q1": {
      "QUESTION": ["차량의 주행거리가 높아도 괜찮으신가요?"],
      "QUEST": {
        "QUESTION_NUMBER": ["1", "2", "3", "4", "5"],
        "QUESTION_VIEW": [
          "많이 뛰었어도 괜찮아요",
          "주행거리가 약간 높아도 괜찮아요",
          "상관없어요",
          "주행거리가 약간 낮은게 좋아요",
          "덜 달린 차가 좋아요"
        ]
      }
    },
    "CONDITION_Q2": {
      "QUESTION": ["차량 상태가 좋다면 가격이 조금 비싸도 괜찮으신가요?"],
      "QUEST": {
        "QUESTION_NUMBER": ["1", "2", "3", "4", "5"],
        "QUESTION_VIEW": [
          "싼게 좋아요",
          "조금 싼게 좋아요",
          "상관없어요",
          "조금 비싸도 괜찮아요",
          "조건이 좋으면 비싸도 좋아요"
        ]
      }
    },
    "CONDITION_Q3": {
      "QUESTION": ["차량 설명을 자세하게 보고 싶나요?"],
      "QUEST": {
        "QUESTION_NUMBER": ["1", "2", "3", "4", "5"],
        "QUESTION_VIEW": [
          "신경쓰지 않아요",
          "조금이라도 적어주세요",
          "상관없어요",
          "대략적으로 적어주세요",
          "자세하게 적어주세요"
        ]
      }
    },
    "CONDITION_Q4": {
      "QUESTION": ["차량마다 자세한 사진을 보고 싶으신가요?"],
      "QUEST": {
        "QUESTION_NUMBER": ["1", "2", "3", "4", "5"],
        "QUESTION_VIEW": [
          "신경쓰지 않아요",
          "간단히 봐도 돼요",
          "상관없어요",
          "약간 자세히 보고싶어요",
          "자세히 보고싶어요"
        ]
      }
    }
  },
  "ASSET": {
    "ASSET_Q1": {
      "QUESTION": ["직거래 차량을 원하시나요?"],
      "QUEST": {
        "QUESTION_NUMBER": ["1", "2", "3", "4", "5"],
        "QUESTION_VIEW": [
          "아니요",
          "별로에요",
          "그냥 그래요",
          "괜찮은거 같아요",
          "좋아요"
        ]
      }
    },
    "ASSET_Q2": {
      "QUESTION": ["하루에 보통 몇 시간 일할 예정이신가요?"],
      "QUEST": {
        "QUESTION_NUMBER": ["1", "2", "3", "4", "5"],
        "QUESTION_VIEW": [
          "3 ~ 6시간",
          "6 ~ 9시간",
          "9 ~ 12시간",
          "12 ~ 15시간",
          "15 ~ 18시간"
        ]
      }
    },
    "ASSET_Q3": {
      "QUESTION": ["한 달에 보통 며칠을 일할 예정이신가요?"],
      "QUEST": {
        "QUESTION_NUMBER": ["1", "2", "3", "4", "5"],
        "QUESTION_VIEW": [
          "10 ~ 14일",
          "14 ~ 18일",
          "18 ~ 22일",
          "22 ~ 26일",
          "26 ~ 30일"
        ]
      }
    }
  }
}
